fdnpy/__init__.py
fdnpy/client.py
fdnpy-0.2.0.dist-info/METADATA
fdnpy-0.2.0.dist-info/WHEEL
fdnpy-0.2.0.dist-info/top_level.txt
fdnpy-0.2.0.dist-info/RECORD
