Metadata-Version: 2.1
Name: fdnpy
Version: 0.2.0
Summary: A Python SDK for FinancialData.Net API
Home-page: https://github.com/financialdatanet/fdnpy
License: UNKNOWN
Platform: UNKNOWN
Classifier: Programming Language :: Python :: 3
Classifier: License :: OSI Approved :: MIT License
Classifier: Operating System :: OS Independent
Requires-Python: >=3.6
Requires-Dist: requests (>=2.25.0)
